{
 "_meta": {},
 "translations": [
  {
   "hash": "aa4a1d49cc1f0334",
   "zh": "一位身材矮小、穿著貝殼製成的華美背心之男子。",
   "note": "DESC"
  },
  {
   "hash": "f517d564b6ac4428",
   "zh": "「現在是打架時間。說話的事待會兒再說。」"
  },
  {
   "hash": "1f917e9f4e3ab99e",
   "zh": "「哦，你好，$G。汝又是哪位？」"
  },
  {
   "hash": "62a296acbfcce5d7",
   "zh": "「幸會，$G $Z。讓吾為汝說個@tale故事。」"
  },
  {
   "hash": "fdfced260eaba549",
   "zh": "「哦，那名字倒是需要一個故事來配。」"
  },
  {
   "hash": "e18ca56008e64755",
   "zh": "「哦，你好，$P。吾跟汝說過那個吉普賽人的故事嗎？」"
  },
  {
   "hash": "f2aea71179d11bd8",
   "zh": "「哦。那來首@song（歌）何。」"
  },
  {
   "hash": "077f398b77a8e588",
   "zh": "「那才是個@tale故事。」"
  },
  {
   "hash": "338bf26a822e3f05",
   "zh": "「吾名卡翰，$G。」"
  },
  {
   "hash": "9a429e352670a856",
   "zh": "「當眾人@spirits（意氣）消沉，吾便奏起樂曲帶來@cheer（歡愉）。」"
  },
  {
   "hash": "d761c00c7d3ea308",
   "zh": "「吾曾聽見一段縈繞不去的旋律……」"
  },
  {
   "hash": "034f446033407e4b",
   "zh": "「……在舊@Magincia（馬精）西亞。」他大笑。",
   "note": "ghost town pun"
  },
  {
   "hash": "962790f67bc41bb1",
   "zh": "「嗯，那裡曾是個鬼城。」",
   "note": "haunting/ghost double pun"
  },
  {
   "hash": "3bbc33f689089ad6",
   "zh": "他大笑，並在魯特琴上撥弄了一段小曲。",
   "note": "action"
  },
  {
   "hash": "7a841c0d5d5760d8",
   "zh": "「勇敢真言帶來無限歡愉。」"
  },
  {
   "hash": "022c9106eb6a7408",
   "zh": "「吾算不上什麼了不起的歌手，但吾愛演奏勇氣之歌。」"
  },
  {
   "hash": "c1c73c46904df188",
   "zh": "「它令吾想要@sing（高歌）。」"
  },
  {
   "hash": "84f4ea166e9614c9",
   "zh": "「吾來唱，雖然吾更想@play（演奏）。」"
  },
  {
   "hash": "133917726d39fb7b",
   "zh": "酒館中歌聲響徹。",
   "note": "action"
  },
  {
   "hash": "b8fbdef507e15667",
   "zh": "卡翰為汝高聲吟唱。",
   "note": "action"
  },
  {
   "hash": "33585622ff007475",
   "zh": "「看似輕而易舉的攀登",
   "note": "song verse 1 line 1"
  },
  {
   "hash": "62855ccc63d43615",
   "zh": "吾爬上了巨蛇脊背",
   "note": "song verse 1 line 2; Serpent's Spine = mountain range"
  },
  {
   "hash": "7c0b5ac09a3ff396",
   "zh": "連臉色發白的時間都沒有",
   "note": "song verse 1 line 3"
  },
  {
   "hash": "5df0a278783371fe",
   "zh": "雪崩轟然而至！」",
   "note": "song verse 1 line 4"
  },
  {
   "hash": "c9065c42d386df91",
   "zh": "「然後真言浮現心頭",
   "note": "song verse 2 line 1"
  },
  {
   "hash": "6ab189d2417a5adf",
   "zh": "巨石橫飛呼嘯而過。",
   "note": "song verse 2 line 2"
  },
  {
   "hash": "e75e30d6a37083a2",
   "zh": "吾凍僵的手指緊抓岩石",
   "note": "song verse 2 line 3"
  },
  {
   "hash": "f8a467b1342aedeb",
   "zh": "流雪將吾雙腳帶走。」",
   "note": "song verse 2 line 4"
  },
  {
   "hash": "7a0f4b36a801824e",
   "zh": "「齊唱『ra』，吾友，齊唱『ra』。",
   "note": "mantra 'ra' revealed; stays as-is"
  },
  {
   "hash": "56c15323385f6dba",
   "zh": "此歌令汝強壯",
   "note": "song chorus"
  },
  {
   "hash": "11a8348486e73e4f",
   "zh": "當群山高聳"
  },
  {
   "hash": "89f54eaae9c511e8",
   "zh": "而地面遙遠……」"
  },
  {
   "hash": "c0a66cb275f022cd",
   "zh": "「……齊唱『ra』，吾友，齊唱『ra』！」",
   "note": "song chorus repeat; mantra 'ra' kept as-is"
  },
  {
   "hash": "98938e059e22f47c",
   "zh": "「啊，是的。那也是個精彩的故事。」",
   "note": "rune/rat story"
  },
  {
   "hash": "a8e9eb56a257ef74",
   "zh": "「頑劣諾曼把勇敢符文掉了，老鼠把它叼走了。」"
  },
  {
   "hash": "81b7a8647f0028ab",
   "zh": "他放聲大笑。",
   "note": "action"
  },
  {
   "hash": "926de206c0ae760f",
   "zh": "笑得太大聲了。史塔赫姆與傑里斯開始爭論那是老鼠還是鼷鼠。",
   "note": "action"
  },
  {
   "hash": "0f5f6fc06a684fa8",
   "zh": "又一場鬥毆爆發了！",
   "note": "action"
  },
  {
   "hash": "e64f996609154134",
   "zh": "「願吾等不久後再相見，朋友。」",
   "note": "bye"
  },
  {
   "hash": "e851d8f398efeabe",
   "zh": "「抱歉，吾無法在此事上助汝。」"
  },
  {
   "hash": "7f4ca881c11de0ba",
   "zh": "「汝真的想聽故事嗎？」"
  },
  {
   "hash": "9d45f37260d8712c",
   "zh": "「嗯，不是每個人都喜歡吉普賽故事，吾想。」"
  },
  {
   "hash": "062fe1acdbb68ce1",
   "zh": "「吾稱這個故事為……」"
  },
  {
   "hash": "575e0e0641409503",
   "zh": "「阿圖羅病症」",
   "note": "fictional disease name"
  },
  {
   "hash": "a3dab12b03158a57",
   "zh": "「兩個吉普賽人來到特林希克，一如往常地飢腸轆轆。」"
  },
  {
   "hash": "c6379476b05eebed",
   "zh": "「一人出去，從沼澤中採集了有毒的野草。」"
  },
  {
   "hash": "47095f8185be2c75",
   "zh": "「另一人偷偷溜進城，把那草放入一匹馬的水槽裡。」"
  },
  {
   "hash": "c278fd299c1beb59",
   "zh": "「可憐的馬什麼都不懂。」"
  },
  {
   "hash": "dc1abc36049416f9",
   "zh": "「牠吃了那東西，腫了起來，病倒了。」"
  },
  {
   "hash": "8553c64976327adb",
   "zh": "「馬的主人伊曼紐爾不知所措。」"
  },
  {
   "hash": "eac192e56f702c02",
   "zh": "「吉普賽人隨即趕來。他們大呼：『哎呀！』」"
  },
  {
   "hash": "591c853948b81d75",
   "zh": "「『那匹駑馬染上了「阿圖羅病症」。』」"
  },
  {
   "hash": "0408c91f791f5f4b",
   "zh": "「『若不立即移除，其餘牲口皆將染上此致命之疾。』」"
  },
  {
   "hash": "44809f812a9c300a",
   "zh": "「伊曼紐爾決定犧牲那匹病馬，吉普賽人欣然同意。」"
  },
  {
   "hash": "a38ee38554c39116",
   "zh": "「『只需幾枚銅幣，』吉普賽人說，『吾等將牠帶走，葬於遠處。』」"
  },
  {
   "hash": "3ed7f02337f581ca",
   "zh": "「伊曼紐爾高高興興地把那倒楣牲口的韁繩交給他們，再加上十枚銅幣。」"
  },
  {
   "hash": "e519ccfee93dc316",
   "zh": "「於是吉普賽人燉了一大鍋馬肉湯，把剩下的埋了。」"
  },
  {
   "hash": "6be275fa59eedd46",
   "zh": "「吉普賽族中大擺宴席。」"
  },
  {
   "hash": "d4427b3bbea04099",
   "zh": "「與此同時，伊曼紐爾感謝美德的庇護，馬瘟發現得如此之早！」"
  },
  {
   "hash": "d4a0e2acfd5bcfb4",
   "zh": "「此乃真實故事，吾友。」"
  }
 ],
 "glossary_additions": {
  "people": {
   "Culham": "卡翰",
   "Jerris": "傑里斯",
   "Immanuelle": "伊曼紐爾"
  },
  "places": {
   "Serpent's Spine": "巨蛇脊背"
  },
  "concepts": {
   "gypsy": "吉普賽人"
  }
 },
 "translator_notes": "卡翰是個說故事兼演奏的遊吟詩人，語氣快活詼諧。歌詞保留意象，真言「ra」以原文呈現（遊戲機制字）。吉普賽故事幽默地揭示吉普賽人的詭計，伊曼紐爾受騙。Serpent's Spine 為山脈名。"
}
