{
 "_meta": {},
 "translations": [
  {
   "hash": "08e0b2f9b1863b72",
   "zh": "一位穿著樸素的吟遊詩人。",
   "note": "DESC; Iolo's wife"
  },
  {
   "hash": "dd2dff756e252640",
   "zh": "「有什麼是汝需要知道的嗎？」"
  },
  {
   "hash": "6366d01424efdfaf",
   "zh": "「你好，$P。」"
  },
  {
   "hash": "e67b001ed446e048",
   "zh": "「是吾，葛溫諾。汝離開吾等的王國很久了，對嗎……」"
  },
  {
   "hash": "56c2105b05d4b242",
   "zh": "「尤洛的@apprentice（學徒）已接手吾在@Iolo（尤洛）弓箭店的工作。」"
  },
  {
   "hash": "5c011085fa737081",
   "zh": "「近來吾一直在為工匠@songs（公會），將不列顛尼亞的民間@notation（歌謠）轉錄成數字@guild（公會）法。」"
  },
  {
   "hash": "15bf157cbc95eaaa",
   "zh": "「當然，眼下協助汝完成任務比那更重要。」"
  },
  {
   "hash": "4c9eb3112bc9501e",
   "zh": "「當然，若汝需要吾的幫助，吾可以暫別公會，@join（加入）汝。」"
  },
  {
   "hash": "ff953eebd939799f",
   "zh": "「@Selganor（瑟爾）嘉諾比吾更能告訴汝關於公會的事。」"
  },
  {
   "hash": "b028a81536dad2e2",
   "zh": "「他是公會會長。」"
  },
  {
   "hash": "2f964d69fb0cc4c5",
   "zh": "「一個民族的歌謠是其文化遺產的重要組成部分。」"
  },
  {
   "hash": "2b33cae27775e4db",
   "zh": "「將它們記錄在紙上，有助於為後代保存吾等的@traditions（傳統）。」"
  },
  {
   "hash": "6870371b13b6ad86",
   "zh": "「吾很高興汝理解傳統的價值。」"
  },
  {
   "hash": "8bf7cb82c4a6da6f",
   "zh": "「有點蓬頭垢面，但他是吾所能期望最可愛的丈夫。」",
   "note": "about Iolo"
  },
  {
   "hash": "87589eb2bbeaa285",
   "zh": "尤洛說：「汝這樣說，只是因為這是實話。」他吻了她一下。",
   "note": "action; Iolo speaks"
  },
  {
   "hash": "48d9b676ada9cb9e",
   "zh": "「若汝需要一把好弩，店就在不列顛城，藍野豬@Boar（酒館）附近。」"
  },
  {
   "hash": "d215a26864407331",
   "zh": "「那是個熱鬧的地方。」",
   "note": "about Blue Boar"
  },
  {
   "hash": "a8b84f1c9a196c62",
   "zh": "「每個@note（音符）對應一個數字，每個數字對應一個@number（音符）。」",
   "note": "numerical notation explanation"
  },
  {
   "hash": "603ef6db5e17735f",
   "zh": "「每個音符由一個@number（數字）表示。」"
  },
  {
   "hash": "a885773043eb9464",
   "zh": "「每個數字@represents（對應）一個@note（音符）。」"
  },
  {
   "hash": "5784bbdcc94b84cc",
   "zh": "「吾就知道汝能理解！」"
  },
  {
   "hash": "b90ab3d2af7d8f79",
   "zh": "「哦，瑟爾嘉諾派汝來的嗎？吾猜汝想學@Stones《石頭》。」"
  },
  {
   "hash": "70667c9d7508f5a7",
   "zh": "「以標準數字記譜法，它是『678987 8767653』。」",
   "note": "Stones melody; numbers kept as-is"
  },
  {
   "hash": "e087373e6efddea1",
   "zh": "「很高興與汝交談。」",
   "note": "bye"
  },
  {
   "hash": "57346b898671370f",
   "zh": "「抱歉，那件事吾幫不上忙。」"
  },
  {
   "hash": "aea535b1fd159b77",
   "zh": "「吾已經加入汝了！」",
   "note": "already in party"
  },
  {
   "hash": "2ce1477fe1d58dfa",
   "zh": "「汝要吾跟汝同行嗎？」"
  },
  {
   "hash": "b73d13fd817a4df6",
   "zh": "「好吧。若之後需要吾，儘管告訴吾。」",
   "note": "not joining"
  },
  {
   "hash": "93597ddbd33dae43",
   "zh": "「只要汝還在那東西裡，吾就不加入！」",
   "note": "on ship"
  },
  {
   "hash": "39c75dbe3f1c1d09",
   "zh": "「汝已經有足夠的同行者了。」",
   "note": "party full"
  },
  {
   "hash": "414a2aeac0b5108c",
   "zh": "「若汝請他們中的一人先@leave（離開），吾很樂意加入。」"
  },
  {
   "hash": "bc3367e0aa14c03f",
   "zh": "「好！再次踏上旅途真是太好了。」",
   "note": "joining"
  },
  {
   "hash": "259d4d9de48a091f",
   "zh": "她跑過去挽著@Iolo（尤洛）的手臂，兩人轉啊轉地跳舞。",
   "note": "action; joining with Iolo"
  },
  {
   "hash": "bcca76d72f370e20",
   "zh": "他們顯然非常高興再次相見。",
   "note": "action"
  },
  {
   "hash": "f5f504e3c07c71e9",
   "zh": "「吾得先@join（加入）汝，才能談離開，傻瓜！」",
   "note": "can't leave without joining"
  },
  {
   "hash": "30179362e7308693",
   "zh": "「讓吾等先回到陸地上再說，好嗎？」",
   "note": "at sea"
  },
  {
   "hash": "f002c5ab8ed65cff",
   "zh": "「好吧。吾回密諾克的家了。若你之後需要吾再次加入，來告訴吾。」",
   "note": "leaving party"
  },
  {
   "hash": "4ebbd5b4d3288478",
   "zh": "「吾把所有東西留在這裡——有些或許對汝有用。」"
  },
  {
   "hash": "934722b2901ad880",
   "zh": "她離去前給了尤洛一個大大的擁抱。",
   "note": "action"
  },
  {
   "hash": "cbaae464c1c0c7a3",
   "zh": "「記得保持襪子乾燥，」她說，「任務結束時再見。」",
   "note": "farewell to Iolo"
  }
 ],
 "glossary_additions": {
  "people": {
   "Gwenno": "葛溫諾"
  },
  "places": {
   "Iolo's Bows": "尤洛弓箭店"
  },
  "concepts": {
   "numerical notation": "數字記譜法",
   "Stones": "《石頭》"
  }
 },
 "translator_notes": "葛溫諾是尤洛的妻子，現任職密諾克工匠公會，將民間歌謠轉錄成數字記譜法。她能教導《石頭》曲調（678987 8767653），這是加入公會的必要條件。她和尤洛的感情甜蜜，相遇時的互動令人動容。"
}
