{
 "_meta": {},
 "translations": [
  {
   "hash": "e3de8ff24a1b54f7",
   "zh": "惡魔辛弗拉。",
   "note": "DESC"
  },
  {
   "hash": "5d6e68452cb09a69",
   "zh": "「$T好，$G。汝尋何物？」"
  },
  {
   "hash": "9d76eacc4733a269",
   "zh": "「吾乃辛弗拉。」"
  },
  {
   "hash": "5629ff4a96b45d5c",
   "zh": "「無職，$G。吾@自由，可隨意遊蕩。」"
  },
  {
   "hash": "bded3ab1be11e788",
   "zh": "「在吾的@族人之中，能飛者統治一切。」"
  },
  {
   "hash": "b71231f7adf7e87e",
   "zh": "「雖然吾有翅膀，卻不能@飛翔。因此吾曾是奴隸。」"
  },
  {
   "hash": "e9f6c0dea840ece7",
   "zh": "「在這裡吾是自由的！」"
  },
  {
   "hash": "815275ae0824f273",
   "zh": "「吾並非惡魔，雖然人類如此以為。」"
  },
  {
   "hash": "5a67784e9b5188c1",
   "zh": "「吾是@魔像族。」"
  },
  {
   "hash": "ab2b937a1ccb6554",
   "zh": "「吾逃到地下世界，因為在魔像族中吾沒有自由。」"
  },
  {
   "hash": "fdcce3bb2c2db500",
   "zh": "「《預言之書》記載，偽先知將到來，摧毀魔像族。」"
  },
  {
   "hash": "ea8255cd85e1d027",
   "zh": "「唯有偽先知的@獻祭，方能拯救吾等。」"
  },
  {
   "hash": "75a85715e1bbdb69",
   "zh": "「因為吾不能@飛翔，所以從未被教導讀書。」"
  },
  {
   "hash": "b7ed14810d2551bb",
   "zh": "「獻祭在吾的語言中有許多含義。」",
   "note": "避免「許」作尾字：此處「許多含義」為四字，「義」為尾字，安全"
  },
  {
   "hash": "381ddb2fc459ae4c",
   "zh": "「汝應尋訪魔像族學者以獲取更多資訊。」"
  },
  {
   "hash": "0eb1b87e460fdf1d",
   "zh": "「前往世界的另一端，汝應能找到一位。」"
  },
  {
   "hash": "34397d746e144d79",
   "zh": "「汝可穿越希斯洛斯下行，進入魔像族的領域。」"
  },
  {
   "hash": "f331b0c22100817d",
   "zh": "「魔像族分兩種：有翅者與無翅者。」"
  },
  {
   "hash": "f468d15b764970a1",
   "zh": "「無翅者啞口且無智，承擔所有體力勞動。」"
  },
  {
   "hash": "ebc44e0a6a84d4c5",
   "zh": "「有翅者聰慧，負責所有謀劃與領導。」"
  },
  {
   "hash": "d11af11ad6e38431",
   "zh": "「在他們看來，能飛翔是@智慧的象徵。」"
  },
  {
   "hash": "34e5ad4c419bfea9",
   "zh": "「甚至連@神殿也只能從空中抵達。」"
  },
  {
   "hash": "db2d7956ba394899",
   "zh": "「是的，這是個奇特的觀念。」"
  },
  {
   "hash": "cf09c58d3345994e",
   "zh": "「然而如敏諾克的某些人會告訴汝，飛翔乃人人可達成之事。」",
   "note": "熱氣球暗示"
  },
  {
   "hash": "8083d7aecbe03d3b",
   "zh": "「偉大的獨一神殿曾供奉守則之書。」"
  },
  {
   "hash": "536b32a5dbe6b53a",
   "zh": "「神殿是魔像族最神聖的場所。」"
  },
  {
   "hash": "d3874df335bff00a",
   "zh": "「人類若前往那裡，定能學到良多。」"
  },
  {
   "hash": "6ba57cda4e985d7f",
   "zh": "「但汝永遠無法抵達神殿。」"
  },
  {
   "hash": "9cedc003a1ee4b2f",
   "zh": "「它不僅深埋於地下，而且只能從空中抵達。」"
  },
  {
   "hash": "44a99199221e9ba2",
   "zh": "「而汝與吾同樣無法飛翔。」"
  },
  {
   "hash": "c1a58ffe5943f1d5",
   "zh": "「是的，吾曾在沙漠中遇到一個海盜。」"
  },
  {
   "hash": "a1f05b0dc5f568f8",
   "zh": "「他似乎在追獵吾，但被@螞蟻拖走了！」"
  },
  {
   "hash": "e935fd11d36a11c1",
   "zh": "「巨型沙漠螞蟻築起龐大的蟻丘，極為危險！」"
  },
  {
   "hash": "5c9cba6a50fd2a8d",
   "zh": "「願汝以堅毅與精確走向成功，$G！」",
   "note": "魔像族告別語套式"
  },
  {
   "hash": "3dfd124bb44724ea",
   "zh": "「吾對$Z一無所知，$G。」"
  }
 ],
 "glossary_additions": {
  "people": {
   "Sin'Vraal": "辛弗拉"
  },
  "places": {
   "Hythloth": "希斯洛斯"
  }
 },
 "translator_notes": "辛弗拉是無翅的自由魔像族，逃至沙漠。提供重要的魔像族社會結構資訊（有翅/無翅、神殿、預言之書）。用文言敬語（「汝/吾」）表現其莊重外星文化感。"
}
